{
  "view": "course",
  "id": "rec9fXNGxN5UAt46h",
  "rowType": "course",
  "title": "Geography: Grade 1",
  "subject": "Geography",
  "gradeText": "GRADE(S): 1",
  "sortId": "",
  "bookCount": 6,
  "sections": [
    {
      "type": "course",
      "id": "rec9fXNGxN5UAt46h",
      "title": "Geography: Grade 1",
      "books": [
        {
          "resourceId": "rec3qRa2nl8pKXiYq",
          "instanceKey": "course:rec9fXNGxN5UAt46h:resource:rec3qRa2nl8pKXiYq",
          "title": "What Makes Day and Night",
          "author": "Franklyn M. Branley",
          "isbn": "",
          "asin": "",
          "imagePath": "img/resources/rec3qRa2nl8pKXiYq.webp",
          "placeholderPath": "img/placeholders/book.svg",
          "optional": false,
          "chooseOne": false,
          "formatTags": "Audiobook",
          "rationale": "Through diagrams, pictures, and simple text, this book helps students gain a better understanding of how the rotation of the earth gives us day and night.",
          "notes": "",
          "scopeText": "Term 1 (Partial Term)",
          "sharedText": "",
          "links": []
        },
        {
          "resourceId": "recG6wPkZfXSJqcPA",
          "instanceKey": "course:rec9fXNGxN5UAt46h:resource:recG6wPkZfXSJqcPA",
          "title": "Elementary Geography",
          "author": "Charlotte Mason",
          "isbn": "",
          "asin": "",
          "imagePath": "img/resources/recG6wPkZfXSJqcPA.webp",
          "placeholderPath": "img/placeholders/book.svg",
          "optional": false,
          "chooseOne": false,
          "formatTags": "Ebook, Audiobook",
          "rationale": "This is Charlotte Mason's classic introduction to Geography. We use selections from the book, which include many demonstrations, to help young children understand the concepts.",
          "notes": "",
          "scopeText": "Term 1 (Selections)\nTerm 2 (Selections)\nTerm 3 (Selections)",
          "sharedText": "",
          "links": []
        },
        {
          "resourceId": "reciSkse5xWCUfLKF",
          "instanceKey": "course:rec9fXNGxN5UAt46h:resource:reciSkse5xWCUfLKF",
          "title": "Me on the Map",
          "author": "Joan Sweeney",
          "isbn": "",
          "asin": "",
          "imagePath": "img/resources/reciSkse5xWCUfLKF.webp",
          "placeholderPath": "img/placeholders/book.svg",
          "optional": false,
          "chooseOne": false,
          "formatTags": "Ebook",
          "rationale": "This book explains the many ways in which we can describe where we are located. Beginning in a little girl's room, we gradually zoom out to her house, her street, her town, her state, her country, and her planet.",
          "notes": "",
          "scopeText": "Term 1 (Partial Term)",
          "sharedText": "",
          "links": []
        },
        {
          "resourceId": "reczH8uwlnf97SywN",
          "instanceKey": "course:rec9fXNGxN5UAt46h:resource:reczH8uwlnf97SywN",
          "title": "United States Atlas 7th Ed.",
          "author": "National Geographic Kids",
          "isbn": "",
          "asin": "",
          "imagePath": "img/resources/reczH8uwlnf97SywN.webp",
          "placeholderPath": "img/placeholders/book.svg",
          "optional": false,
          "chooseOne": false,
          "formatTags": "",
          "rationale": "This atlas is used across the curriculum as a reference and as a text to read in some lessons. With interesting information and pictures, this is an economical reference for students.",
          "notes": "",
          "scopeText": "Term 1\nTerm 2\nTerm 3",
          "sharedText": "Geography: Grade 1\nGeography: Grade 7 (U.S.)\nResources: Grade 9\nResources: Grade 10\nResources: Grade 11\nResources: Grade 12\nGeography: Grade 2 (U.S.)\nGeography: Grade 3 (U.S.)\nGeography: Grade 8 (U.S.)",
          "links": []
        },
        {
          "resourceId": "recvkrUbkJpCJfW9f",
          "instanceKey": "course:rec9fXNGxN5UAt46h:resource:recvkrUbkJpCJfW9f",
          "title": "The Reasons for Seasons",
          "author": "Gail Gibbons",
          "isbn": "",
          "asin": "",
          "imagePath": "img/resources/recvkrUbkJpCJfW9f.webp",
          "placeholderPath": "img/placeholders/book.svg",
          "optional": false,
          "chooseOne": false,
          "formatTags": "Ebook, Audiobook",
          "rationale": "This book is a great introduction to seasons, the earth's orbit, and axial tilt.",
          "notes": "",
          "scopeText": "Term 2 (Partial Term)",
          "sharedText": "",
          "links": []
        },
        {
          "resourceId": "recenxHB4rtNnHx4p",
          "instanceKey": "course:rec9fXNGxN5UAt46h:resource:recenxHB4rtNnHx4p",
          "title": "Down Comes the Rain",
          "author": "Franklyn M. Branley",
          "isbn": "",
          "asin": "",
          "imagePath": "img/resources/recenxHB4rtNnHx4p.webp",
          "placeholderPath": "img/placeholders/book.svg",
          "optional": false,
          "chooseOne": false,
          "formatTags": "Ebook, Audiobook",
          "rationale": "This is a great book for students to learn about the water cycle. There are clear explanations and great illustrations.",
          "notes": "",
          "scopeText": "Term 3 (Partial Term)",
          "sharedText": "",
          "links": []
        }
      ]
    }
  ]
}
