{
  "view": "course",
  "id": "reccEm8T5hzKrWrUH",
  "recordID": "reccEm8T5hzKrWrUH",
  "courseRecordId": "reccEm8T5hzKrWrUH",
  "Sort_ID": "",
  "legacyId": "reccEm8T5hzKrWrUH",
  "courseLegacyId": "reccEm8T5hzKrWrUH",
  "rowType": "course",
  "title": "Geography: Grade 3 (Canada)",
  "subject": "Geography",
  "gradeText": "GRADE(S): 3",
  "schedText": "2 times/week 20 min * 🅃",
  "shared": false,
  "sortId": "",
  "bookCount": 3,
  "sections": [
    {
      "type": "course",
      "id": "reccEm8T5hzKrWrUH",
      "recordID": "reccEm8T5hzKrWrUH",
      "courseRecordId": "reccEm8T5hzKrWrUH",
      "Sort_ID": "",
      "legacyId": "reccEm8T5hzKrWrUH",
      "courseLegacyId": "reccEm8T5hzKrWrUH",
      "title": "Geography: Grade 3 (Canada)",
      "gradeText": "GRADE(S): 3",
      "schedText": "2 times/week 20 min * 🅃",
      "shared": false,
      "sortId": "",
      "books": [
        {
          "resourceId": "recgECwMa1pjs2VnL",
          "instanceKey": "course:reccEm8T5hzKrWrUH:resource:recgECwMa1pjs2VnL",
          "title": "The Kids Book of Canada",
          "author": "Barbara Greenwood",
          "isbn": "978-1554532261",
          "asin": "",
          "isbnAsin": "978-1554532261",
          "imagePath": "img/resources/recgECwMa1pjs2VnL.webp",
          "placeholderPath": "img/placeholders/book.svg",
          "optional": false,
          "chooseOne": false,
          "gradeLevelTag": "",
          "formatTags": "",
          "formatOptions": [],
          "rationale": "This book gives an engaging overview of Canada's ten provinces and three territories and includes maps, geographical features, important facts, symbols, significant people, places, and events.",
          "noteText": "",
          "maySubText": "",
          "discountText": "",
          "scopeText": "Term 1\nTerm 2\nTerm 3",
          "sharedText": "Geography: Grade 2 (Canada)\nGeography: Grade 3 (Canada)",
          "purchaseOptions": [
            {
              "label": "Option 1",
              "url": "https://www.amazon.ca/dp/1554532264?bestFormat=true&newOGT=1&linkCode=ll2&tag=alveary0a-20&linkId=c1e30220f405a9d366910d5a6fb049e8&ref_=as_li_ss_tl",
              "memberOnly": false,
              "memberstackId": ""
            },
            {
              "label": "Option 2",
              "url": "https://www.indigo.ca/en-ca/the-kids-book-of-canada/9781554532261.html",
              "memberOnly": false,
              "memberstackId": ""
            }
          ]
        },
        {
          "resourceId": "recWe8BWvLumLf1DA",
          "instanceKey": "course:reccEm8T5hzKrWrUH:resource:recWe8BWvLumLf1DA",
          "title": "My Canada: An Illustrated Atlas",
          "author": "Katherine Dearlove",
          "isbn": "978-1771473774",
          "asin": "",
          "isbnAsin": "978-1771473774",
          "imagePath": "img/resources/recWe8BWvLumLf1DA.webp",
          "placeholderPath": "img/placeholders/book.svg",
          "optional": false,
          "chooseOne": false,
          "gradeLevelTag": "",
          "formatTags": "",
          "formatOptions": [],
          "rationale": "A visually appealing atlas for young learners, this fun book makes a good companion to studying the provinces in The Kids Book of Canada.",
          "noteText": "",
          "maySubText": "",
          "discountText": "",
          "scopeText": "Term 1\nTerm 2\nTerm 3",
          "sharedText": "Geography: Grade 2 (Canada)\nGeography: Grade 3 (Canada)",
          "purchaseOptions": [
            {
              "label": "Option 1",
              "url": "https://www.amazon.ca/dp/1771473770?social_share=cm_sw_r_ffobk_cp_ud_dp_FXX89V1PPRTH1QN80HXM&bestFormat=true&newOGT=1&linkCode=ll2&tag=alveary0a-20&linkId=3666dda59a78212e11c7f6c551fd59cb&ref_=as_li_ss_tl",
              "memberOnly": false,
              "memberstackId": ""
            }
          ]
        },
        {
          "resourceId": "recXRFY35nX9sYw2c",
          "instanceKey": "course:reccEm8T5hzKrWrUH:resource:recXRFY35nX9sYw2c",
          "title": "Canada Wild: Animals Found Nowhere Else on Earth",
          "author": "Maria Birmingham",
          "isbn": "978-1774711132",
          "asin": "",
          "isbnAsin": "978-1774711132",
          "imagePath": "img/resources/recXRFY35nX9sYw2c.webp",
          "placeholderPath": "img/placeholders/book.svg",
          "optional": false,
          "chooseOne": false,
          "gradeLevelTag": "",
          "formatTags": "Ebook",
          "formatOptions": [
            {
              "type": "ebook",
              "label": "Ebook"
            }
          ],
          "rationale": "This colourful, illustrated guide to Canada's endemic species introduces young readers to twelve special animals that can only be found in Canada and who have much to teach us about the varied ecosystems that make up our country.",
          "noteText": "",
          "maySubText": "",
          "discountText": "",
          "scopeText": "Term 1 (Partial Term)\nTerm 2 (Partial Term)\nTerm 3 (Partial Term)",
          "sharedText": "Geography: Grade 2 (Canada)\nGeography: Grade 3 (Canada)",
          "purchaseOptions": [
            {
              "label": "Option 1",
              "url": "https://www.amazon.ca/dp/1774711133?bestFormat=true&newOGT=1&linkCode=ll2&tag=alveary0a-20&linkId=fd2fcf5b494e9335c21037b89506c8c2&ref_=as_li_ss_tl",
              "memberOnly": false,
              "memberstackId": ""
            },
            {
              "label": "Option 2",
              "url": "https://www.indigo.ca/en-ca/canada-wild-animals-found-nowhere-else-on-earth/9781774711132.html",
              "memberOnly": false,
              "memberstackId": ""
            }
          ]
        }
      ]
    }
  ]
}
