{
  "view": "course",
  "id": "recnP198FoIW9MXSu",
  "rowType": "course",
  "title": "Recitation: Grade 12",
  "subject": "English",
  "gradeText": "GRADE(S): 12",
  "sortId": "",
  "bookCount": 1,
  "sections": [
    {
      "type": "course",
      "id": "recnP198FoIW9MXSu",
      "title": "Recitation: Grade 12",
      "books": [
        {
          "resourceId": "recsNwud3Tci78Te8",
          "instanceKey": "course:recnP198FoIW9MXSu:resource:recsNwud3Tci78Te8",
          "title": "Our Work: Grades 9-12",
          "author": "Alveary",
          "isbn": "",
          "asin": "",
          "imagePath": "img/resources/recsNwud3Tci78Te8.webp",
          "placeholderPath": "img/placeholders/book.svg",
          "optional": false,
          "chooseOne": false,
          "formatTags": "Ebook",
          "rationale": "This is a compilation of the year's Recitation, Picture Study, Hymns, Spirituals, and Folk Songs. Line drawings of artifacts from the historical time period are also included to provide students with inspiration for their Book of Centuries. We recommend printing or purchasing a copy for each student.",
          "notes": "",
          "scopeText": "Term 1\nTerm 2\nTerm 3",
          "sharedText": "Recitation: Grade 9\nRecitation: Grade 10\nRecitation: Grade 11\nRecitation: Grade 12\nMusic: Level 5\nPicture Study",
          "links": []
        }
      ]
    }
  ]
}
