{
  "view": "course",
  "id": "recphzOz02QtwWmTI",
  "rowType": "course",
  "title": "Sewing: Level 2",
  "subject": "Life Skills",
  "gradeText": "GRADE(S): 4-6",
  "sortId": "",
  "bookCount": 1,
  "sections": [
    {
      "type": "course",
      "id": "recphzOz02QtwWmTI",
      "title": "Sewing: Level 2",
      "books": [
        {
          "resourceId": "recvU9fKQ6yED22ln",
          "instanceKey": "course:recphzOz02QtwWmTI:resource:recvU9fKQ6yED22ln",
          "title": "The Amazing Stitching Handbook for Kids: 17 Embroidery Stitches",
          "author": "Kristin Nicholas",
          "isbn": "",
          "asin": "",
          "imagePath": "img/resources/recvU9fKQ6yED22ln.webp",
          "placeholderPath": "img/placeholders/book.svg",
          "optional": false,
          "chooseOne": false,
          "formatTags": "Ebook",
          "rationale": "This book contains embroidery stitches that can be added to sewing projects.",
          "notes": "",
          "scopeText": "Term 1\nTerm 2\nTerm 3",
          "sharedText": "",
          "links": []
        }
      ]
    }
  ]
}
