{
  "view": "course",
  "id": "recqv7ncp4qei07K0",
  "recordID": "recqv7ncp4qei07K0",
  "courseRecordId": "recqv7ncp4qei07K0",
  "Sort_ID": "",
  "legacyId": "recqv7ncp4qei07K0",
  "courseLegacyId": "recqv7ncp4qei07K0",
  "rowType": "course",
  "title": "Geography: Grade 2 (Canada)",
  "subject": "Geography",
  "gradeText": "GRADE(S): 2",
  "schedText": "2 times/week 20 min * 🅃",
  "shared": false,
  "sortId": "",
  "bookCount": 5,
  "sections": [
    {
      "type": "course",
      "id": "recqv7ncp4qei07K0",
      "recordID": "recqv7ncp4qei07K0",
      "courseRecordId": "recqv7ncp4qei07K0",
      "Sort_ID": "",
      "legacyId": "recqv7ncp4qei07K0",
      "courseLegacyId": "recqv7ncp4qei07K0",
      "title": "Geography: Grade 2 (Canada)",
      "gradeText": "GRADE(S): 2",
      "schedText": "2 times/week 20 min * 🅃",
      "shared": false,
      "sortId": "",
      "books": [
        {
          "resourceId": "rec4S3UHWafRPSXxM",
          "instanceKey": "course:recqv7ncp4qei07K0:resource:rec4S3UHWafRPSXxM",
          "title": "Making Your Own Maps",
          "author": "Susan Hansen",
          "isbn": "978-1666349665",
          "asin": "",
          "isbnAsin": "978-1666349665",
          "imagePath": "img/resources/rec4S3UHWafRPSXxM.webp",
          "placeholderPath": "img/placeholders/book.svg",
          "optional": false,
          "chooseOne": false,
          "gradeLevelTag": "",
          "formatTags": "Ebook, Audiobook",
          "formatOptions": [
            {
              "type": "ebook",
              "label": "Ebook"
            },
            {
              "type": "audiobook",
              "label": "Audiobook"
            }
          ],
          "rationale": "This book provides great examples of different kinds of maps that students will be creating in their geography lessons.",
          "noteText": "Teachers may wish to check this book out from the library rather than purchase it, as it is only used for a couple of lessons.",
          "maySubText": "",
          "discountText": "",
          "scopeText": "Term 1 (Partial Term)\nTerm 3 (One Lesson)",
          "sharedText": "Geography: Grade 2 (U.S.)\nGeography: Grade 2 (Canada)",
          "purchaseOptions": [
            {
              "label": "Option 1",
              "url": "https://www.amazon.com/dp/1666349666?psc=1&linkCode=ll2&tag=alveary0a-20&linkId=e64dd9c4d71452378aab912e2e8ba4f6&language=en_US&ref_=as_li_ss_tl",
              "memberOnly": false,
              "memberstackId": ""
            },
            {
              "label": "Option 2",
              "url": "https://bookshop.org/a/90084/9781666349665",
              "memberOnly": false,
              "memberstackId": ""
            }
          ]
        },
        {
          "resourceId": "recgECwMa1pjs2VnL",
          "instanceKey": "course:recqv7ncp4qei07K0:resource:recgECwMa1pjs2VnL",
          "title": "The Kids Book of Canada",
          "author": "Barbara Greenwood",
          "isbn": "978-1554532261",
          "asin": "",
          "isbnAsin": "978-1554532261",
          "imagePath": "img/resources/recgECwMa1pjs2VnL.webp",
          "placeholderPath": "img/placeholders/book.svg",
          "optional": false,
          "chooseOne": false,
          "gradeLevelTag": "",
          "formatTags": "",
          "formatOptions": [],
          "rationale": "This book gives an engaging overview of Canada's ten provinces and three territories and includes maps, geographical features, important facts, symbols, significant people, places, and events.",
          "noteText": "",
          "maySubText": "",
          "discountText": "",
          "scopeText": "Term 1\nTerm 2\nTerm 3",
          "sharedText": "Geography: Grade 2 (Canada)\nGeography: Grade 3 (Canada)",
          "purchaseOptions": [
            {
              "label": "Option 1",
              "url": "https://www.amazon.ca/dp/1554532264?bestFormat=true&newOGT=1&linkCode=ll2&tag=alveary0a-20&linkId=c1e30220f405a9d366910d5a6fb049e8&ref_=as_li_ss_tl",
              "memberOnly": false,
              "memberstackId": ""
            },
            {
              "label": "Option 2",
              "url": "https://www.indigo.ca/en-ca/the-kids-book-of-canada/9781554532261.html",
              "memberOnly": false,
              "memberstackId": ""
            }
          ]
        },
        {
          "resourceId": "recWe8BWvLumLf1DA",
          "instanceKey": "course:recqv7ncp4qei07K0:resource:recWe8BWvLumLf1DA",
          "title": "My Canada: An Illustrated Atlas",
          "author": "Katherine Dearlove",
          "isbn": "978-1771473774",
          "asin": "",
          "isbnAsin": "978-1771473774",
          "imagePath": "img/resources/recWe8BWvLumLf1DA.webp",
          "placeholderPath": "img/placeholders/book.svg",
          "optional": false,
          "chooseOne": false,
          "gradeLevelTag": "",
          "formatTags": "",
          "formatOptions": [],
          "rationale": "A visually appealing atlas for young learners, this fun book makes a good companion to studying the provinces in The Kids Book of Canada.",
          "noteText": "",
          "maySubText": "",
          "discountText": "",
          "scopeText": "Term 1\nTerm 2\nTerm 3",
          "sharedText": "Geography: Grade 2 (Canada)\nGeography: Grade 3 (Canada)",
          "purchaseOptions": [
            {
              "label": "Option 1",
              "url": "https://www.amazon.ca/dp/1771473770?social_share=cm_sw_r_ffobk_cp_ud_dp_FXX89V1PPRTH1QN80HXM&bestFormat=true&newOGT=1&linkCode=ll2&tag=alveary0a-20&linkId=3666dda59a78212e11c7f6c551fd59cb&ref_=as_li_ss_tl",
              "memberOnly": false,
              "memberstackId": ""
            }
          ]
        },
        {
          "resourceId": "recXRFY35nX9sYw2c",
          "instanceKey": "course:recqv7ncp4qei07K0:resource:recXRFY35nX9sYw2c",
          "title": "Canada Wild: Animals Found Nowhere Else on Earth",
          "author": "Maria Birmingham",
          "isbn": "978-1774711132",
          "asin": "",
          "isbnAsin": "978-1774711132",
          "imagePath": "img/resources/recXRFY35nX9sYw2c.webp",
          "placeholderPath": "img/placeholders/book.svg",
          "optional": false,
          "chooseOne": false,
          "gradeLevelTag": "",
          "formatTags": "Ebook",
          "formatOptions": [
            {
              "type": "ebook",
              "label": "Ebook"
            }
          ],
          "rationale": "This colourful, illustrated guide to Canada's endemic species introduces young readers to twelve special animals that can only be found in Canada and who have much to teach us about the varied ecosystems that make up our country.",
          "noteText": "",
          "maySubText": "",
          "discountText": "",
          "scopeText": "Term 1 (Partial Term)\nTerm 2 (Partial Term)\nTerm 3 (Partial Term)",
          "sharedText": "Geography: Grade 2 (Canada)\nGeography: Grade 3 (Canada)",
          "purchaseOptions": [
            {
              "label": "Option 1",
              "url": "https://www.amazon.ca/dp/1774711133?bestFormat=true&newOGT=1&linkCode=ll2&tag=alveary0a-20&linkId=fd2fcf5b494e9335c21037b89506c8c2&ref_=as_li_ss_tl",
              "memberOnly": false,
              "memberstackId": ""
            },
            {
              "label": "Option 2",
              "url": "https://www.indigo.ca/en-ca/canada-wild-animals-found-nowhere-else-on-earth/9781774711132.html",
              "memberOnly": false,
              "memberstackId": ""
            }
          ]
        },
        {
          "resourceId": "recBW8QJCHsV0XMoM",
          "instanceKey": "course:recqv7ncp4qei07K0:resource:recBW8QJCHsV0XMoM",
          "title": "Our Canadian Flag",
          "author": "Maxine Trottier",
          "isbn": "978-0439956871",
          "asin": "",
          "isbnAsin": "978-0439956871",
          "imagePath": "img/resources/recBW8QJCHsV0XMoM.webp",
          "placeholderPath": "img/placeholders/book.svg",
          "optional": false,
          "chooseOne": false,
          "gradeLevelTag": "",
          "formatTags": "",
          "formatOptions": [],
          "rationale": "This book offers a patriotic look at the Canadian flag by exploring its history and significance for the whole country. Each page is beautifully illustrated and addresses a different theme by presenting both a narrative description and specific facts and examples that can provide interesting avenues for further learning.",
          "noteText": "",
          "maySubText": "",
          "discountText": "",
          "scopeText": "Term 3",
          "sharedText": "",
          "purchaseOptions": [
            {
              "label": "Option 1",
              "url": "https://www.amazon.ca/dp/0439956870?bestFormat=true&newOGT=1&linkCode=ll2&tag=alveary0a-20&linkId=9a45524d9aa208bd7a3d09750e59ee24&ref_=as_li_ss_tl",
              "memberOnly": false,
              "memberstackId": ""
            }
          ]
        }
      ]
    }
  ]
}
